radoneye/__init__.py
radoneye/__main__.py
radoneye/cli.py
radoneye/client.py
radoneye/debug.py
radoneye/interface_v1.py
radoneye/interface_v2.py
radoneye/model.py
radoneye/py.typed
radoneye/scanner.py
radoneye/util.py
radoneye-2.0.2.dist-info/LICENSE
radoneye-2.0.2.dist-info/METADATA
radoneye-2.0.2.dist-info/WHEEL
radoneye-2.0.2.dist-info/entry_points.txt
radoneye-2.0.2.dist-info/top_level.txt
radoneye-2.0.2.dist-info/RECORD
