Metadata-Version: 2.2
Name: radoneye
Version: 2.0.2
Summary: API and CLI for Ecosense RadonEye devices
Author-email: Artem Butusov <art.sormy@gmail.com>
License: MIT License
Project-URL: Homepage, https://github.com/sormy/radoneye
Project-URL: Issues, https://github.com/sormy/radoneye/issues
Keywords: Ecosense,RadonEye,RD200
Classifier: License :: OSI Approved :: MIT License
Classifier: Programming Language :: Python
Classifier: Programming Language :: Python :: 3
Requires-Python: >=3.9
License-File: LICENSE
Requires-Dist: asyncio<4.0.0,>=3.4.3
Requires-Dist: bleak<1.0.0,>=0.21.1
